[
  {
    "id": "96sErVjEN7LNJ6Uvj63bdRWZxNuBngj56fnT9biHLKBf|0xSOL",
    "wallet": "96sErVjEN7LNJ6Uvj63bdRWZxNuBngj56fnT9biHLKBf",
    "token_name": "SOL",
    "token_address": "0xSOL",
    "first_trade": "2023-09-01T10:00:00Z",
    "last_trade": "2023-09-15T12:00:00Z",
    "buys": 5,
    "sells": 3,
    "invested_sol": 20.5,
    "invested_sol_usd": 500,
    "realized_pnl": 2.5,
    "realized_pnl_usd": 60,
    "roi": 15,
    "name": "Orangie",
    "avatar": "/orangie.jpg",
    "followers": 279
  },
  {
    "id": "96sErVjEN7LNJ6Uvj63bdRWZxNuBngj56fnT9biHLKBf|0xBTC",
    "wallet": "96sErVjEN7LNJ6Uvj63bdRWZxNuBngj56fnT9biHLKBf",
    "token_name": "BTC",
    "token_address": "0xBTC",
    "first_trade": "2023-09-03T11:00:00Z",
    "last_trade": "2023-09-16T14:30:00Z",
    "buys": 3,
    "sells": 2,
    "invested_sol": 30.2,
    "invested_sol_usd": 750,
    "realized_pnl": 4.2,
    "realized_pnl_usd": 105,
    "roi": 18,
    "name": "Orangie",
    "avatar": "/orangie.jpg",
    "followers": 279
  },
  {
    "id": "96sErVjEN7LNJ6Uvj63bdRWZxNuBngj56fnT9biHLKBf|0xETH",
    "wallet": "96sErVjEN7LNJ6Uvj63bdRWZxNuBngj56fnT9biHLKBf",
    "token_name": "ETH",
    "token_address": "0xETH",
    "first_trade": "2023-09-05T09:00:00Z",
    "last_trade": "2023-09-17T16:45:00Z",
    "buys": 4,
    "sells": 1,
    "invested_sol": 15.8,
    "invested_sol_usd": 390,
    "realized_pnl": 1.8,
    "realized_pnl_usd": 45,
    "roi": 12,
    "name": "Orangie",
    "avatar": "/orangie.jpg",
    "followers": 279
  },
  {
    "id": "3fxdghbb|0xBTC",
    "wallet": "3fxdghbb",
    "token_name": "BTC",
    "token_address": "0xBTC",
    "first_trade": "2023-09-03T08:00:00Z",
    "last_trade": "2023-09-17T08:30:00Z",
    "buys": 10,
    "sells": 7,
    "invested_sol": 50,
    "invested_sol_usd": 1000,
    "realized_pnl": 8,
    "realized_pnl_usd": 200,
    "roi": 25,
    "name": "John Doe",
    "avatar": "https://example.com/johndoe-avatar.png"
  },
  {
    "id": "0xDEF456|0xETH",
    "wallet": "0xDEF456",
    "token_name": "ETH",
    "token_address": "0xETH",
    "first_trade": "2023-09-05T09:30:00Z",
    "last_trade": "2023-09-16T11:00:00Z",
    "buys": 8,
    "sells": 4,
    "invested_sol": 35,
    "invested_sol_usd": 800,
    "realized_pnl": 5.2,
    "realized_pnl_usd": 120,
    "roi": 20
  },
  {
    "id": "0x789ABC|0xADA",
    "wallet": "0x789ABC",
    "token_name": "ADA",
    "token_address": "0xADA",
    "first_trade": "2023-09-02T14:15:00Z",
    "last_trade": "2023-09-14T15:00:00Z",
    "buys": 6,
    "sells": 2,
    "invested_sol": 22,
    "invested_sol_usd": 550,
    "realized_pnl": 1.8,
    "realized_pnl_usd": 45,
    "roi": 10
  },
  {
    "id": "0x333444|0xDOT",
    "wallet": "0x333444",
    "token_name": "DOT",
    "token_address": "0xDOT",
    "first_trade": "2023-09-04T11:00:00Z",
    "last_trade": "2023-09-18T11:15:00Z",
    "buys": 3,
    "sells": 5,
    "invested_sol": 15,
    "invested_sol_usd": 400,
    "realized_pnl": -1,
    "realized_pnl_usd": -25,
    "roi": -5
  }
] 